dialoaders/__init__.py
dialoaders/loaders.py
judgyrag/__init__.py
judgyrag/benchgen.py
judgyrag/preproc/judgypdf.py
judgyrag/utils/generate.py
judgyrag/utils/postproc.py
fundialogues-0.1.0.dist-info/LICENSE
fundialogues-0.1.0.dist-info/METADATA
fundialogues-0.1.0.dist-info/WHEEL
fundialogues-0.1.0.dist-info/top_level.txt
fundialogues-0.1.0.dist-info/RECORD
