Metadata-Version: 2.1
Name: fundialogues
Version: 0.1.0
Summary: A library of datasets, LLM tooling, and open source models that can be used for training and inference for prototyping purposes.
Author-email: Eduardo Andres Alvarez <eduand.alvarez@gmail.com>
License: Apache License
Project-URL: Homepage, https://github.com/eduand-alvarez/fun-dialogues/tree/main
Keywords: rag,genai,datasets,prototyping,ai
Classifier: License :: OSI Approved :: Apache Software License
Classifier: Programming Language :: Python
Classifier: Programming Language :: Python :: 3
Requires-Python: >=3.9.0
License-File: LICENSE
Requires-Dist: transformers >=4.31.0
Requires-Dist: accelerate >=0.21.0
Requires-Dist: pandas >=2.2.0
Requires-Dist: pypdf2 >=3.0.1
Requires-Dist: datasets >=2.17.0
